descriptive_meta_tags/__init__.py
flaskbb_plugin_descriptive_meta_tags-0.0.2.dist-info/METADATA
flaskbb_plugin_descriptive_meta_tags-0.0.2.dist-info/RECORD
flaskbb_plugin_descriptive_meta_tags-0.0.2.dist-info/WHEEL
flaskbb_plugin_descriptive_meta_tags-0.0.2.dist-info/entry_points.txt
flaskbb_plugin_descriptive_meta_tags-0.0.2.dist-info/top_level.txt
